etc/provision.sh
jobs.py
poetry.lock
labster/__init__.py
labster/app.py
labster/auth.py
labster/bi/__init__.py
labster/bi/model.py
labster/bi/synchro.py
labster/blueprints/__init__.py
labster/blueprints/auth/__init__.py
labster/blueprints/auth/backdoors.py
labster/blueprints/auth/cas.py
labster/blueprints/auth/templates/auth/login.j2
labster/blueprints/auth/templates/auth/login_cas.j2
labster/blueprints/auth/templates/auth/redirect.j2
labster/blueprints/auth/templates/auth/single_user.j2
labster/blueprints/backup.py
labster/blueprints/bi/__init__.py
labster/blueprints/bi/forms.py
labster/blueprints/bi/model.py
labster/blueprints/bi/synchro.py
labster/blueprints/bi/templates/bi/home.html
labster/blueprints/bi/util.py
labster/blueprints/bi/views.py
labster/blueprints/logging/__init__.py
labster/blueprints/logging/templates/logs/index.j2
labster/blueprints/main.py
labster/blueprints/notifications/__init__.py
labster/blueprints/notifications/mails.py
labster/blueprints/notifications/templates/notifications/debug/notifications.html
labster/blueprints/notifications/templates/notifications/debug/recaps.html
labster/blueprints/notifications/templates/notifications/email/notifications.html
labster/blueprints/notifications/templates/notifications/email/recap-actions.html
labster/blueprints/notifications/templates/notifications/email/recap-new.html
labster/blueprints/notifications/views.py
labster/blueprints/v3/__init__.py
labster/blueprints/v3/test_api.py
labster/blueprints/v3/user/__init__.py
labster/blueprints/v3/user/preferences.py
labster/bus/__init__.py
labster/cli/__init__.py
labster/cli/commands.py
labster/cli/indexing.py
labster/cli/restheart.py
labster/cli/testing.py
labster/config.py
labster/conftest.py
labster/debug.py
labster/di.py
labster/domain/__init__.py
labster/domain/models/__init__.py
labster/domain/models/config.py
labster/domain/models/demandes.py
labster/domain/models/faq.py
labster/domain/models/financeurs.py
labster/domain/models/mapping_dgrtt.py
labandco-2.2.35.dist-info/LICENSE.txt
labandco-2.2.35.dist-info/METADATA
labandco-2.2.35.dist-info/WHEEL
labandco-2.2.35.dist-info/entry_points.txt
labandco-2.2.35.dist-info/RECORD
