Metadata-Version: 2.1
Name: labandco
Version: 2.2.35
Summary: solution métier pour fluidifier les relations entre chercheurs et administration dans les universités et les EPST
Author: Abilian SAS
Requires-Python: >=3.10,<4.0
Classifier: Programming Language :: Python :: 3
Classifier: Programming Language :: Python :: 3.10
Classifier: Programming Language :: Python :: 3.11
Classifier: Programming Language :: Python :: 3.12
Requires-Dist: Flask-WeasyPrint
Requires-Dist: abilian-core (>=0.11.24)
Requires-Dist: apispec (==6.3.0)
Requires-Dist: apscheduler (>=3.6.3,<4.0.0)
Requires-Dist: attrs
Requires-Dist: cairocffi (>=1.4.0,<2.0.0)
Requires-Dist: devtools
Requires-Dist: diskcache (>=4.1.0,<5.0.0)
Requires-Dist: dotted
Requires-Dist: email_validator
Requires-Dist: flask-assets (<2)
Requires-Dist: flask-babel (<2)
Requires-Dist: flask-injector
Requires-Dist: flask-profiler (>=1.8,<2.0)
Requires-Dist: flask-redis
Requires-Dist: flask-smorest
Requires-Dist: glom
Requires-Dist: gunicorn (<20)
Requires-Dist: html2text
Requires-Dist: inflection
Requires-Dist: iso8601
Requires-Dist: jsonrpcserver (>=4.2.0,<5.0.0)
Requires-Dist: ldif (>=4.1.3,<5.0.0)
Requires-Dist: loguru (>=0.6.0,<0.7.0)
Requires-Dist: markupsafe (>=2,<2.1)
Requires-Dist: marshmallow (<3)
Requires-Dist: marshmallow-annotations
Requires-Dist: marshmallow-sqlalchemy
Requires-Dist: more-itertools
Requires-Dist: pampy (>=0.3.0,<0.4.0)
Requires-Dist: pandas (>=1.5.0,<2.0.0)
Requires-Dist: psycopg2
Requires-Dist: python-dotenv (>=0.10.5,<0.11.0)
Requires-Dist: ramda (>=0.5.9,<0.6.0)
Requires-Dist: requests[security] (>=2.28.1,<3.0.0)
Requires-Dist: structlog
Requires-Dist: toolz
Requires-Dist: werkzeug (<1)
Requires-Dist: wtforms (<3)
